hyperlink_prediction/__init__.py
hyperlink_prediction/hyperlink_prediction_algorithm.py
hyperlink_prediction/hyperlink_prediction_base.py
hyperlink_prediction/hyperlink_prediction_result.py
hyperlink_prediction/datasets/__init__.py
hyperlink_prediction/datasets/arb_dataset.py
hyperlink_prediction/datasets/dataset_hypergraph.py
hyperlink_prediction/datasets/imdb_dataset.py
hyperlink_prediction/loader/__init__.py
hyperlink_prediction/loader/dataloader.py
negative_sampling/__init__.py
negative_sampling/hypergraph_negative_sampling.py
negative_sampling/hypergraph_negative_sampling_algorithm.py
negative_sampling/hypergraph_negative_sampling_result.py
pipelines/__init__.py
pipelines/imdb_pipeline.py
utils/__init__.py
utils/hyperlink_train_test_split.py
utils/set_negative_samplig_method.py
hypernegative-0.1.2.6.dist-info/METADATA
hypernegative-0.1.2.6.dist-info/WHEEL
hypernegative-0.1.2.6.dist-info/entry_points.txt
hypernegative-0.1.2.6.dist-info/top_level.txt
hypernegative-0.1.2.6.dist-info/RECORD
