Metadata-Version: 2.4
Name: hypernegative
Version: 0.1.2.6
Author-email: Giovanni Semioli <g.semioli1@studenti.unisa.it>
Project-URL: Homepage, https://www.isislab.it/
Project-URL: Repository, https://github.com/hypernetwork-research-group/hypernegative
Project-URL: Issue Tracker, https://github.com/hypernetwork-research-group/hypernegative/issues
Requires-Python: >=3.13
Requires-Dist: gdown>=5.2.0
Requires-Dist: numpy>=2.3.3
Requires-Dist: scikit-learn>=1.7.2
Requires-Dist: seaborn>=0.13.2
Requires-Dist: tensorboard>=2.20.0
